NodeSocket/NodeSocket.py
NodeSocket/__init__.py
NodeSocket-0.3.2.dist-info/LICENSE
NodeSocket-0.3.2.dist-info/METADATA
NodeSocket-0.3.2.dist-info/WHEEL
NodeSocket-0.3.2.dist-info/top_level.txt
NodeSocket-0.3.2.dist-info/RECORD
